<?xml version="1.0" encoding="UTF-8"?>
<export version="E">
  <design>
    <source>C:\Users\Mehmet Şahin\Desktop\KİCAD PROJECTS\FLIP_FLOP\FLIP_FLOP\FLIP_FLOP.kicad_sch</source>
    <date>20.12.2023 16:40:23</date>
    <tool>Eeschema 7.0.9</tool>
    <sheet number="1" name="/" tstamps="/">
      <title_block>
        <title/>
        <company/>
        <rev/>
        <date/>
        <source>FLIP_FLOP.kicad_sch</source>
        <comment number="1" value=""/>
        <comment number="2" value=""/>
        <comment number="3" value=""/>
        <comment number="4" value=""/>
        <comment number="5" value=""/>
        <comment number="6" value=""/>
        <comment number="7" value=""/>
        <comment number="8" value=""/>
        <comment number="9" value=""/>
      </title_block>
    </sheet>
  </design>
  <components>
    <comp ref="C1">
      <value>10uF</value>
      <footprint>Capacitor_THT:CP_Radial_D6.3mm_P2.50mm</footprint>
      <libsource lib="Device" part="C_Polarized_US" description="Polarized capacitor, US symbol"/>
      <property name="Sheetname" value=""/>
      <property name="Sheetfile" value="FLIP_FLOP.kicad_sch"/>
      <property name="ki_description" value="Polarized capacitor, US symbol"/>
      <property name="ki_keywords" value="cap capacitor"/>
      <sheetpath names="/" tstamps="/"/>
      <tstamps>68f202de-136c-4f1d-ac95-494de5562a0a</tstamps>
    </comp>
    <comp ref="C2">
      <value>0.1uF</value>
      <footprint>Capacitor_THT:C_Disc_D3.0mm_W1.6mm_P2.50mm</footprint>
      <libsource lib="Device" part="C_Small" description="Unpolarized capacitor, small symbol"/>
      <property name="Sheetname" value=""/>
      <property name="Sheetfile" value="FLIP_FLOP.kicad_sch"/>
      <property name="ki_description" value="Unpolarized capacitor, small symbol"/>
      <property name="ki_keywords" value="capacitor cap"/>
      <sheetpath names="/" tstamps="/"/>
      <tstamps>974dc79b-20c0-4957-aca6-19cefffc58cb</tstamps>
    </comp>
    <comp ref="D1">
      <value>LED</value>
      <footprint>LED_THT:LED_D3.0mm</footprint>
      <libsource lib="Device" part="LED" description="Light emitting diode"/>
      <property name="Sheetname" value=""/>
      <property name="Sheetfile" value="FLIP_FLOP.kicad_sch"/>
      <property name="ki_description" value="Light emitting diode"/>
      <property name="ki_keywords" value="LED diode"/>
      <sheetpath names="/" tstamps="/"/>
      <tstamps>1d66f6e1-46f9-481b-9aa9-8f1bed55d7ad</tstamps>
    </comp>
    <comp ref="D2">
      <value>LED</value>
      <footprint>LED_THT:LED_D3.0mm</footprint>
      <libsource lib="Device" part="LED" description="Light emitting diode"/>
      <property name="Sheetname" value=""/>
      <property name="Sheetfile" value="FLIP_FLOP.kicad_sch"/>
      <property name="ki_description" value="Light emitting diode"/>
      <property name="ki_keywords" value="LED diode"/>
      <sheetpath names="/" tstamps="/"/>
      <tstamps>17ff6c06-9a77-4b51-81e3-4e99cbad892f</tstamps>
    </comp>
    <comp ref="J2">
      <value>PWR</value>
      <footprint>Connector_Molex:Molex_KK-254_AE-6410-02A_1x02_P2.54mm_Vertical</footprint>
      <libsource lib="Connector" part="Conn_01x02_Pin" description="Generic connector, single row, 01x02, script generated"/>
      <property name="Sheetname" value=""/>
      <property name="Sheetfile" value="FLIP_FLOP.kicad_sch"/>
      <property name="ki_description" value="Generic connector, single row, 01x02, script generated"/>
      <property name="ki_keywords" value="connector"/>
      <sheetpath names="/" tstamps="/"/>
      <tstamps>5b26d1ec-f251-4f79-94c4-9cf314bd1903</tstamps>
    </comp>
    <comp ref="R1">
      <value>330</value>
      <footprint>Resistor_THT:R_Axial_DIN0204_L3.6mm_D1.6mm_P5.08mm_Horizontal</footprint>
      <libsource lib="Device" part="R" description="Resistor"/>
      <property name="Sheetname" value=""/>
      <property name="Sheetfile" value="FLIP_FLOP.kicad_sch"/>
      <property name="ki_description" value="Resistor"/>
      <property name="ki_keywords" value="R res resistor"/>
      <sheetpath names="/" tstamps="/"/>
      <tstamps>d0597553-b57d-483b-a4d1-7a6f14943571</tstamps>
    </comp>
    <comp ref="R2">
      <value>330</value>
      <footprint>Resistor_THT:R_Axial_DIN0204_L3.6mm_D1.6mm_P5.08mm_Horizontal</footprint>
      <libsource lib="Device" part="R" description="Resistor"/>
      <property name="Sheetname" value=""/>
      <property name="Sheetfile" value="FLIP_FLOP.kicad_sch"/>
      <property name="ki_description" value="Resistor"/>
      <property name="ki_keywords" value="R res resistor"/>
      <sheetpath names="/" tstamps="/"/>
      <tstamps>be8701b8-1fac-4da0-9a0f-6ecb103fb5fd</tstamps>
    </comp>
    <comp ref="R3">
      <value>100k</value>
      <footprint>Resistor_THT:R_Axial_DIN0204_L3.6mm_D1.6mm_P5.08mm_Horizontal</footprint>
      <libsource lib="Device" part="R" description="Resistor"/>
      <property name="Sheetname" value=""/>
      <property name="Sheetfile" value="FLIP_FLOP.kicad_sch"/>
      <property name="ki_description" value="Resistor"/>
      <property name="ki_keywords" value="R res resistor"/>
      <sheetpath names="/" tstamps="/"/>
      <tstamps>fce2f15d-19b2-4247-ac18-df4498f95519</tstamps>
    </comp>
    <comp ref="R4">
      <value>50k</value>
      <footprint>Resistor_THT:R_Axial_DIN0204_L3.6mm_D1.6mm_P5.08mm_Horizontal</footprint>
      <libsource lib="Device" part="R" description="Resistor"/>
      <property name="Sheetname" value=""/>
      <property name="Sheetfile" value="FLIP_FLOP.kicad_sch"/>
      <property name="ki_description" value="Resistor"/>
      <property name="ki_keywords" value="R res resistor"/>
      <sheetpath names="/" tstamps="/"/>
      <tstamps>8b3db565-3b03-4e20-97ec-4ef2726f0317</tstamps>
    </comp>
    <comp ref="U1">
      <value>NE555P</value>
      <footprint>Package_DIP:DIP-8_W7.62mm_LongPads</footprint>
      <datasheet>http://www.ti.com/lit/ds/symlink/ne555.pdf</datasheet>
      <libsource lib="Timer" part="NE555P" description="Precision Timers, 555 compatible,  PDIP-8"/>
      <property name="Sheetname" value=""/>
      <property name="Sheetfile" value="FLIP_FLOP.kicad_sch"/>
      <property name="ki_description" value="Precision Timers, 555 compatible,  PDIP-8"/>
      <property name="ki_keywords" value="single timer 555"/>
      <sheetpath names="/" tstamps="/"/>
      <tstamps>0ce50280-c18e-456e-98b4-156e852e6bd0</tstamps>
    </comp>
  </components>
  <libparts>
    <libpart lib="Connector" part="Conn_01x02_Pin">
      <description>Generic connector, single row, 01x02, script generated</description>
      <docs>~</docs>
      <footprints>
        <fp>Connector*:*_1x??_*</fp>
      </footprints>
      <fields>
        <field name="Reference">J</field>
        <field name="Value">Conn_01x02_Pin</field>
        <field name="Datasheet">~</field>
      </fields>
      <pins>
        <pin num="1" name="Pin_1" type="passive"/>
        <pin num="2" name="Pin_2" type="passive"/>
      </pins>
    </libpart>
    <libpart lib="Device" part="C_Polarized_US">
      <description>Polarized capacitor, US symbol</description>
      <docs>~</docs>
      <footprints>
        <fp>CP_*</fp>
      </footprints>
      <fields>
        <field name="Reference">C</field>
        <field name="Value">C_Polarized_US</field>
        <field name="Datasheet">~</field>
      </fields>
      <pins>
        <pin num="1" name="" type="passive"/>
        <pin num="2" name="" type="passive"/>
      </pins>
    </libpart>
    <libpart lib="Device" part="C_Small">
      <description>Unpolarized capacitor, small symbol</description>
      <docs>~</docs>
      <footprints>
        <fp>C_*</fp>
      </footprints>
      <fields>
        <field name="Reference">C</field>
        <field name="Value">C_Small</field>
        <field name="Datasheet">~</field>
      </fields>
      <pins>
        <pin num="1" name="" type="passive"/>
        <pin num="2" name="" type="passive"/>
      </pins>
    </libpart>
    <libpart lib="Device" part="LED">
      <description>Light emitting diode</description>
      <docs>~</docs>
      <footprints>
        <fp>LED*</fp>
        <fp>LED_SMD:*</fp>
        <fp>LED_THT:*</fp>
      </footprints>
      <fields>
        <field name="Reference">D</field>
        <field name="Value">LED</field>
        <field name="Datasheet">~</field>
      </fields>
      <pins>
        <pin num="1" name="K" type="passive"/>
        <pin num="2" name="A" type="passive"/>
      </pins>
    </libpart>
    <libpart lib="Device" part="R">
      <description>Resistor</description>
      <docs>~</docs>
      <footprints>
        <fp>R_*</fp>
      </footprints>
      <fields>
        <field name="Reference">R</field>
        <field name="Value">R</field>
        <field name="Datasheet">~</field>
      </fields>
      <pins>
        <pin num="1" name="" type="passive"/>
        <pin num="2" name="" type="passive"/>
      </pins>
    </libpart>
    <libpart lib="Timer" part="NE555P">
      <description>Precision Timers, 555 compatible,  PDIP-8</description>
      <docs>http://www.ti.com/lit/ds/symlink/ne555.pdf</docs>
      <footprints>
        <fp>DIP*W7.62mm*</fp>
      </footprints>
      <fields>
        <field name="Reference">U</field>
        <field name="Value">NE555P</field>
        <field name="Footprint">Package_DIP:DIP-8_W7.62mm</field>
        <field name="Datasheet">http://www.ti.com/lit/ds/symlink/ne555.pdf</field>
      </fields>
      <pins>
        <pin num="1" name="GND" type="power_in"/>
        <pin num="2" name="TR" type="input"/>
        <pin num="3" name="Q" type="output"/>
        <pin num="4" name="R" type="input"/>
        <pin num="5" name="CV" type="input"/>
        <pin num="6" name="THR" type="input"/>
        <pin num="7" name="DIS" type="input"/>
        <pin num="8" name="VCC" type="power_in"/>
      </pins>
    </libpart>
  </libparts>
  <libraries>
    <library logical="Connector">
      <uri>C:\Program Files\KiCad\7.0\share\kicad\symbols\/Connector.kicad_sym</uri>
    </library>
    <library logical="Device">
      <uri>C:\Program Files\KiCad\7.0\share\kicad\symbols\/Device.kicad_sym</uri>
    </library>
    <library logical="Timer">
      <uri>C:\Program Files\KiCad\7.0\share\kicad\symbols\/Timer.kicad_sym</uri>
    </library>
  </libraries>
  <nets>
    <net code="1" name="+5V">
      <node ref="J2" pin="1" pinfunction="Pin_1" pintype="passive"/>
      <node ref="R1" pin="1" pintype="passive"/>
      <node ref="R3" pin="1" pintype="passive"/>
      <node ref="U1" pin="4" pinfunction="R" pintype="input"/>
      <node ref="U1" pin="8" pinfunction="VCC" pintype="power_in"/>
    </net>
    <net code="2" name="GND">
      <node ref="C1" pin="2" pintype="passive"/>
      <node ref="C2" pin="2" pintype="passive"/>
      <node ref="J2" pin="2" pinfunction="Pin_2" pintype="passive"/>
      <node ref="R2" pin="2" pintype="passive"/>
      <node ref="U1" pin="1" pinfunction="GND" pintype="power_in"/>
    </net>
    <net code="3" name="Net-(D1-A)">
      <node ref="D1" pin="2" pinfunction="A" pintype="passive"/>
      <node ref="R1" pin="2" pintype="passive"/>
    </net>
    <net code="4" name="Net-(D1-K)">
      <node ref="D1" pin="1" pinfunction="K" pintype="passive"/>
      <node ref="D2" pin="2" pinfunction="A" pintype="passive"/>
      <node ref="U1" pin="3" pinfunction="Q" pintype="output"/>
    </net>
    <net code="5" name="Net-(D2-K)">
      <node ref="D2" pin="1" pinfunction="K" pintype="passive"/>
      <node ref="R2" pin="1" pintype="passive"/>
    </net>
    <net code="6" name="Net-(U1-CV)">
      <node ref="C2" pin="1" pintype="passive"/>
      <node ref="U1" pin="5" pinfunction="CV" pintype="input"/>
    </net>
    <net code="7" name="Net-(U1-DIS)">
      <node ref="R3" pin="2" pintype="passive"/>
      <node ref="R4" pin="1" pintype="passive"/>
      <node ref="U1" pin="7" pinfunction="DIS" pintype="input"/>
    </net>
    <net code="8" name="Net-(U1-THR)">
      <node ref="C1" pin="1" pintype="passive"/>
      <node ref="R4" pin="2" pintype="passive"/>
      <node ref="U1" pin="2" pinfunction="TR" pintype="input"/>
      <node ref="U1" pin="6" pinfunction="THR" pintype="input"/>
    </net>
  </nets>
</export>
